{"number":434,"additions":407,"deletions":154,"createdAt":"2021-07-15T17:25:49Z","merged":true,"mergedAt":"2021-07-22T09:59:21Z","closed":true,"closedAt":"2021-07-22T09:59:21Z","author":{"login":"feethamCooper"},"timelineItems":{"totalCount":89},"commits":{"edges":[{"node":{"commit":{"authoredDate":"2021-07-14T13:56:56Z"}}},{"node":{"commit":{"authoredDate":"2021-07-15T10:21:20Z"}}},{"node":{"commit":{"authoredDate":"2021-07-15T13:38:18Z"}}},{"node":{"commit":{"authoredDate":"2021-07-15T13:48:57Z"}}},{"node":{"commit":{"authoredDate":"2021-07-15T14:50:18Z"}}},{"node":{"commit":{"authoredDate":"2021-07-15T17:03:15Z"}}},{"node":{"commit":{"authoredDate":"2021-07-15T17:24:58Z"}}},{"node":{"commit":{"authoredDate":"2021-07-15T17:25:20Z"}}},{"node":{"commit":{"authoredDate":"2021-07-16T09:43:14Z"}}},{"node":{"commit":{"authoredDate":"2021-07-16T13:10:40Z"}}},{"node":{"commit":{"authoredDate":"2021-07-16T13:28:45Z"}}},{"node":{"commit":{"authoredDate":"2021-07-16T13:33:57Z"}}},{"node":{"commit":{"authoredDate":"2021-07-16T16:15:59Z"}}},{"node":{"commit":{"authoredDate":"2021-07-16T16:41:19Z"}}},{"node":{"commit":{"authoredDate":"2021-07-16T16:57:22Z"}}},{"node":{"commit":{"authoredDate":"2021-07-16T16:57:41Z"}}},{"node":{"commit":{"authoredDate":"2021-07-16T17:22:44Z"}}},{"node":{"commit":{"authoredDate":"2021-07-17T21:51:12Z"}}},{"node":{"commit":{"authoredDate":"2021-07-18T17:16:48Z"}}},{"node":{"commit":{"authoredDate":"2021-07-18T18:14:25Z"}}},{"node":{"commit":{"authoredDate":"2021-07-18T18:46:47Z"}}},{"node":{"commit":{"authoredDate":"2021-07-18T19:06:29Z"}}},{"node":{"commit":{"authoredDate":"2021-07-18T20:59:26Z"}}},{"node":{"commit":{"authoredDate":"2021-07-18T21:06:47Z"}}},{"node":{"commit":{"authoredDate":"2021-07-18T21:28:02Z"}}},{"node":{"commit":{"authoredDate":"2021-07-18T22:15:51Z"}}},{"node":{"commit":{"authoredDate":"2021-07-20T08:58:31Z"}}},{"node":{"commit":{"authoredDate":"2021-07-20T09:07:30Z"}}},{"node":{"commit":{"authoredDate":"2021-07-20T09:22:08Z"}}},{"node":{"commit":{"authoredDate":"2021-07-20T09:23:25Z"}}},{"node":{"commit":{"authoredDate":"2021-07-20T11:00:00Z"}}},{"node":{"commit":{"authoredDate":"2021-07-20T11:02:51Z"}}},{"node":{"commit":{"authoredDate":"2021-07-20T11:19:08Z"}}},{"node":{"commit":{"authoredDate":"2021-07-20T11:19:34Z"}}},{"node":{"commit":{"authoredDate":"2021-07-20T15:16:04Z"}}},{"node":{"commit":{"authoredDate":"2021-07-20T15:17:32Z"}}},{"node":{"commit":{"authoredDate":"2021-07-20T15:18:27Z"}}},{"node":{"commit":{"authoredDate":"2021-07-20T15:19:17Z"}}},{"node":{"commit":{"authoredDate":"2021-07-20T15:20:33Z"}}},{"node":{"commit":{"authoredDate":"2021-07-20T15:21:09Z"}}},{"node":{"commit":{"authoredDate":"2021-07-20T15:21:23Z"}}},{"node":{"commit":{"authoredDate":"2021-07-20T15:23:10Z"}}},{"node":{"commit":{"authoredDate":"2021-07-20T15:23:32Z"}}},{"node":{"commit":{"authoredDate":"2021-07-20T15:25:31Z"}}},{"node":{"commit":{"authoredDate":"2021-07-20T15:26:44Z"}}},{"node":{"commit":{"authoredDate":"2021-07-20T15:27:14Z"}}},{"node":{"commit":{"authoredDate":"2021-07-20T15:28:57Z"}}},{"node":{"commit":{"authoredDate":"2021-07-20T15:38:33Z"}}},{"node":{"commit":{"authoredDate":"2021-07-20T15:39:27Z"}}},{"node":{"commit":{"authoredDate":"2021-07-20T16:09:40Z"}}},{"node":{"commit":{"authoredDate":"2021-07-20T16:46:48Z"}}},{"node":{"commit":{"authoredDate":"2021-07-20T16:47:59Z"}}},{"node":{"commit":{"authoredDate":"2021-07-20T16:48:16Z"}}},{"node":{"commit":{"authoredDate":"2021-07-20T16:50:00Z"}}},{"node":{"commit":{"authoredDate":"2021-07-20T16:50:36Z"}}},{"node":{"commit":{"authoredDate":"2021-07-20T16:50:56Z"}}},{"node":{"commit":{"authoredDate":"2021-07-20T16:54:30Z"}}},{"node":{"commit":{"authoredDate":"2021-07-20T16:54:57Z"}}},{"node":{"commit":{"authoredDate":"2021-07-20T16:55:27Z"}}},{"node":{"commit":{"authoredDate":"2021-07-20T16:55:54Z"}}},{"node":{"commit":{"authoredDate":"2021-07-20T16:56:42Z"}}},{"node":{"commit":{"authoredDate":"2021-07-21T09:51:39Z"}}},{"node":{"commit":{"authoredDate":"2021-07-21T09:56:59Z"}}},{"node":{"commit":{"authoredDate":"2021-07-21T13:08:49Z"}}},{"node":{"commit":{"authoredDate":"2021-07-21T13:09:07Z"}}},{"node":{"commit":{"authoredDate":"2021-07-21T13:09:15Z"}}},{"node":{"commit":{"authoredDate":"2021-07-21T13:10:34Z"}}},{"node":{"commit":{"authoredDate":"2021-07-21T13:12:29Z"}}},{"node":{"commit":{"authoredDate":"2021-07-21T13:12:52Z"}}},{"node":{"commit":{"authoredDate":"2021-07-21T13:13:03Z"}}},{"node":{"commit":{"authoredDate":"2021-07-21T13:14:11Z"}}},{"node":{"commit":{"authoredDate":"2021-07-21T13:15:05Z"}}},{"node":{"commit":{"authoredDate":"2021-07-21T13:17:13Z"}}},{"node":{"commit":{"authoredDate":"2021-07-21T13:21:06Z"}}},{"node":{"commit":{"authoredDate":"2021-07-21T13:34:17Z"}}},{"node":{"commit":{"authoredDate":"2021-07-21T13:41:33Z"}}}]},"reviews":{"edges":[{"node":{"createdAt":"2021-07-20T13:56:32Z","commit":{"authoredDate":"2021-07-20T11:19:34Z"}}},{"node":{"createdAt":"2021-07-20T15:18:13Z","commit":{"authoredDate":"2021-07-20T11:19:34Z"}}},{"node":{"createdAt":"2021-07-20T15:19:11Z","commit":{"authoredDate":"2021-07-20T11:19:34Z"}}},{"node":{"createdAt":"2021-07-20T15:20:23Z","commit":{"authoredDate":"2021-07-20T11:19:34Z"}}},{"node":{"createdAt":"2021-07-20T15:26:25Z","commit":{"authoredDate":"2021-07-20T15:23:32Z"}}},{"node":{"createdAt":"2021-07-20T15:27:03Z","commit":{"authoredDate":"2021-07-20T15:25:31Z"}}},{"node":{"createdAt":"2021-07-20T15:28:41Z","commit":{"authoredDate":"2021-07-20T15:27:14Z"}}},{"node":{"createdAt":"2021-07-20T15:33:07Z","commit":{"authoredDate":"2021-07-20T15:27:14Z"}}},{"node":{"createdAt":"2021-07-20T15:33:33Z","commit":{"authoredDate":"2021-07-20T15:27:14Z"}}},{"node":{"createdAt":"2021-07-20T15:37:51Z","commit":{"authoredDate":"2021-07-20T15:28:57Z"}}},{"node":{"createdAt":"2021-07-20T15:40:55Z","commit":{"authoredDate":"2021-07-20T15:38:33Z"}}},{"node":{"createdAt":"2021-07-20T16:45:23Z","commit":{"authoredDate":"2021-07-20T15:39:27Z"}}},{"node":{"createdAt":"2021-07-20T16:53:54Z","commit":{"authoredDate":"2021-07-20T16:50:36Z"}}},{"node":{"createdAt":"2021-07-20T16:57:34Z","commit":{"authoredDate":"2021-07-20T16:56:42Z"}}},{"node":{"createdAt":"2021-07-21T16:04:36Z","commit":{"authoredDate":"2021-07-21T13:41:33Z"}}},{"node":{"createdAt":"2021-07-21T10:14:45Z","commit":{"authoredDate":"2021-07-21T09:51:39Z"}}}]},"comments":{"edges":[{"node":{"author":{"login":"feethamCooper"}}}]},"createdAtDate":"2021-07-15T17:25:49.000Z","mergedAtDate":"2021-07-22T09:59:21.000Z","closedAtDate":"2021-07-22T09:59:21.000Z","churn":{"List":[{"Type":"C","Date":"2021-07-14T13:56:56.000Z"},{"Type":"C","Date":"2021-07-15T10:21:20.000Z"},{"Type":"C","Date":"2021-07-15T13:38:18.000Z"},{"Type":"C","Date":"2021-07-15T13:48:57.000Z"},{"Type":"C","Date":"2021-07-15T14:50:18.000Z"},{"Type":"C","Date":"2021-07-15T17:03:15.000Z"},{"Type":"C","Date":"2021-07-15T17:24:58.000Z"},{"Type":"C","Date":"2021-07-15T17:25:20.000Z"},{"Type":"C","Date":"2021-07-16T09:43:14.000Z"},{"Type":"C","Date":"2021-07-16T13:10:40.000Z"},{"Type":"C","Date":"2021-07-16T13:28:45.000Z"},{"Type":"C","Date":"2021-07-16T13:33:57.000Z"},{"Type":"C","Date":"2021-07-16T16:15:59.000Z"},{"Type":"C","Date":"2021-07-16T16:41:19.000Z"},{"Type":"C","Date":"2021-07-16T16:57:22.000Z"},{"Type":"C","Date":"2021-07-16T16:57:41.000Z"},{"Type":"C","Date":"2021-07-16T17:22:44.000Z"},{"Type":"C","Date":"2021-07-17T21:51:12.000Z"},{"Type":"C","Date":"2021-07-18T17:16:48.000Z"},{"Type":"C","Date":"2021-07-18T18:14:25.000Z"},{"Type":"C","Date":"2021-07-18T18:46:47.000Z"},{"Type":"C","Date":"2021-07-18T19:06:29.000Z"},{"Type":"C","Date":"2021-07-18T20:59:26.000Z"},{"Type":"C","Date":"2021-07-18T21:06:47.000Z"},{"Type":"C","Date":"2021-07-18T21:28:02.000Z"},{"Type":"C","Date":"2021-07-18T22:15:51.000Z"},{"Type":"C","Date":"2021-07-20T08:58:31.000Z"},{"Type":"C","Date":"2021-07-20T09:07:30.000Z"},{"Type":"C","Date":"2021-07-20T09:22:08.000Z"},{"Type":"C","Date":"2021-07-20T09:23:25.000Z"},{"Type":"C","Date":"2021-07-20T11:00:00.000Z"},{"Type":"C","Date":"2021-07-20T11:02:51.000Z"},{"Type":"C","Date":"2021-07-20T11:19:08.000Z"},{"Type":"C","Date":"2021-07-20T11:19:34.000Z"},{"Type":"R","Date":"2021-07-20T13:56:32.000Z"},{"Type":"C","Date":"2021-07-20T15:16:04.000Z"},{"Type":"C","Date":"2021-07-20T15:17:32.000Z"},{"Type":"R","Date":"2021-07-20T15:18:13.000Z"},{"Type":"C","Date":"2021-07-20T15:18:27.000Z"},{"Type":"R","Date":"2021-07-20T15:19:11.000Z"},{"Type":"C","Date":"2021-07-20T15:19:17.000Z"},{"Type":"R","Date":"2021-07-20T15:20:23.000Z"},{"Type":"C","Date":"2021-07-20T15:20:33.000Z"},{"Type":"C","Date":"2021-07-20T15:21:09.000Z"},{"Type":"C","Date":"2021-07-20T15:21:23.000Z"},{"Type":"C","Date":"2021-07-20T15:23:10.000Z"},{"Type":"C","Date":"2021-07-20T15:23:32.000Z"},{"Type":"C","Date":"2021-07-20T15:25:31.000Z"},{"Type":"R","Date":"2021-07-20T15:26:25.000Z"},{"Type":"C","Date":"2021-07-20T15:26:44.000Z"},{"Type":"R","Date":"2021-07-20T15:27:03.000Z"},{"Type":"C","Date":"2021-07-20T15:27:14.000Z"},{"Type":"R","Date":"2021-07-20T15:28:41.000Z"},{"Type":"C","Date":"2021-07-20T15:28:57.000Z"},{"Type":"R","Date":"2021-07-20T15:33:07.000Z"},{"Type":"R","Date":"2021-07-20T15:33:33.000Z"},{"Type":"R","Date":"2021-07-20T15:37:51.000Z"},{"Type":"C","Date":"2021-07-20T15:38:33.000Z"},{"Type":"C","Date":"2021-07-20T15:39:27.000Z"},{"Type":"R","Date":"2021-07-20T15:40:55.000Z"},{"Type":"C","Date":"2021-07-20T16:09:40.000Z"},{"Type":"R","Date":"2021-07-20T16:45:23.000Z"},{"Type":"C","Date":"2021-07-20T16:46:48.000Z"},{"Type":"C","Date":"2021-07-20T16:47:59.000Z"},{"Type":"C","Date":"2021-07-20T16:48:16.000Z"},{"Type":"C","Date":"2021-07-20T16:50:00.000Z"},{"Type":"C","Date":"2021-07-20T16:50:36.000Z"},{"Type":"C","Date":"2021-07-20T16:50:56.000Z"},{"Type":"R","Date":"2021-07-20T16:53:54.000Z"},{"Type":"C","Date":"2021-07-20T16:54:30.000Z"},{"Type":"C","Date":"2021-07-20T16:54:57.000Z"},{"Type":"C","Date":"2021-07-20T16:55:27.000Z"},{"Type":"C","Date":"2021-07-20T16:55:54.000Z"},{"Type":"C","Date":"2021-07-20T16:56:42.000Z"},{"Type":"R","Date":"2021-07-20T16:57:34.000Z"},{"Type":"C","Date":"2021-07-21T09:51:39.000Z"},{"Type":"C","Date":"2021-07-21T09:56:59.000Z"},{"Type":"R","Date":"2021-07-21T10:14:45.000Z"},{"Type":"C","Date":"2021-07-21T13:08:49.000Z"},{"Type":"C","Date":"2021-07-21T13:09:07.000Z"},{"Type":"C","Date":"2021-07-21T13:09:15.000Z"},{"Type":"C","Date":"2021-07-21T13:10:34.000Z"},{"Type":"C","Date":"2021-07-21T13:12:29.000Z"},{"Type":"C","Date":"2021-07-21T13:12:52.000Z"},{"Type":"C","Date":"2021-07-21T13:13:03.000Z"},{"Type":"C","Date":"2021-07-21T13:14:11.000Z"},{"Type":"C","Date":"2021-07-21T13:15:05.000Z"},{"Type":"C","Date":"2021-07-21T13:17:13.000Z"},{"Type":"C","Date":"2021-07-21T13:21:06.000Z"},{"Type":"C","Date":"2021-07-21T13:34:17.000Z"},{"Type":"C","Date":"2021-07-21T13:41:33.000Z"},{"Type":"R","Date":"2021-07-21T16:04:36.000Z"}],"ChurnNumber":14}}