{"number":245,"additions":2,"deletions":4,"changedFiles":1,"createdAt":"2022-08-19T15:59:07Z","merged":true,"mergedAt":"2022-08-19T16:05:51Z","closed":true,"closedAt":"2022-08-19T16:05:51Z","author":{"login":"NateCassidy"},"timelineItems":{"totalCount":12},"commits":{"edges":[{"node":{"commit":{"authoredDate":"2022-08-19T15:58:52Z"}}}]},"reviews":{"edges":[{"node":{"createdAt":"2022-08-19T15:59:46Z","commit":{"authoredDate":"2022-08-19T15:58:52Z"}}},{"node":{"createdAt":"2022-08-19T16:00:38Z","commit":{"authoredDate":"2022-08-19T15:58:52Z"}}},{"node":{"createdAt":"2022-08-19T16:03:50Z","commit":{"authoredDate":"2022-08-19T15:58:52Z"}}},{"node":{"createdAt":"2022-08-19T16:05:14Z","commit":{"authoredDate":"2022-08-19T15:58:52Z"}}}]},"comments":{"edges":[]},"createdAtDate":"2022-08-19T15:59:07.000Z","mergedAtDate":"2022-08-19T16:05:51.000Z","closedAtDate":"2022-08-19T16:05:51.000Z","churn":{"List":[{"Type":"C","Date":"2022-08-19T15:58:52.000Z"},{"Type":"R","Date":"2022-08-19T15:59:46.000Z"},{"Type":"R","Date":"2022-08-19T16:00:38.000Z"},{"Type":"R","Date":"2022-08-19T16:03:50.000Z"},{"Type":"R","Date":"2022-08-19T16:05:14.000Z"}],"ChurnNumber":1}}