{"number":156,"additions":40,"deletions":0,"changedFiles":3,"createdAt":"2022-02-28T10:18:00Z","merged":true,"mergedAt":"2022-03-18T10:49:23Z","closed":true,"closedAt":"2022-03-18T10:49:23Z","author":{"login":"willjatlas"},"timelineItems":{"totalCount":31},"commits":{"edges":[{"node":{"commit":{"authoredDate":"2022-02-28T10:14:41Z"}}},{"node":{"commit":{"authoredDate":"2022-02-28T10:34:34Z"}}},{"node":{"commit":{"authoredDate":"2022-03-01T09:02:00Z"}}},{"node":{"commit":{"authoredDate":"2022-03-01T09:16:47Z"}}},{"node":{"commit":{"authoredDate":"2022-03-17T14:36:53Z"}}}]},"reviews":{"edges":[{"node":{"createdAt":"2022-02-28T10:19:32Z","commit":{"authoredDate":"2022-02-28T10:14:41Z"}}},{"node":{"createdAt":"2022-02-28T11:53:07Z","commit":{"authoredDate":"2022-02-28T10:34:34Z"}}},{"node":{"createdAt":"2022-02-28T17:08:41Z","commit":{"authoredDate":"2022-02-28T10:34:34Z"}}},{"node":{"createdAt":"2022-02-28T17:09:18Z","commit":{"authoredDate":"2022-02-28T10:34:34Z"}}},{"node":{"createdAt":"2022-03-01T09:02:16Z","commit":{"authoredDate":"2022-03-01T09:02:00Z"}}},{"node":{"createdAt":"2022-03-01T09:09:33Z","commit":{"authoredDate":"2022-03-01T09:02:00Z"}}},{"node":{"createdAt":"2022-03-09T09:17:26Z","commit":{"authoredDate":"2022-03-01T09:16:47Z"}}},{"node":{"createdAt":"2022-03-10T11:54:58Z","commit":{"authoredDate":"2022-03-01T09:16:47Z"}}},{"node":{"createdAt":"2022-03-17T14:19:44Z","commit":{"authoredDate":"2022-03-01T09:16:47Z"}}},{"node":{"createdAt":"2022-03-17T15:55:28Z","commit":{"authoredDate":"2022-03-01T09:16:47Z"}}},{"node":{"createdAt":"2022-03-17T16:10:49Z","commit":{"authoredDate":"2022-03-17T14:36:53Z"}}},{"node":{"createdAt":"2022-03-17T16:31:14Z","commit":{"authoredDate":"2022-03-17T14:36:53Z"}}},{"node":{"createdAt":"2022-03-18T10:39:25Z","commit":{"authoredDate":"2022-03-17T14:36:53Z"}}}]},"comments":{"edges":[]},"createdAtDate":"2022-02-28T10:18:00.000Z","mergedAtDate":"2022-03-18T10:49:23.000Z","closedAtDate":"2022-03-18T10:49:23.000Z","churn":{"List":[{"Type":"C","Date":"2022-02-28T10:14:41.000Z"},{"Type":"R","Date":"2022-02-28T10:19:32.000Z"},{"Type":"C","Date":"2022-02-28T10:34:34.000Z"},{"Type":"R","Date":"2022-02-28T11:53:07.000Z"},{"Type":"R","Date":"2022-02-28T17:08:41.000Z"},{"Type":"R","Date":"2022-02-28T17:09:18.000Z"},{"Type":"C","Date":"2022-03-01T09:02:00.000Z"},{"Type":"R","Date":"2022-03-01T09:02:16.000Z"},{"Type":"R","Date":"2022-03-01T09:09:33.000Z"},{"Type":"C","Date":"2022-03-01T09:16:47.000Z"},{"Type":"R","Date":"2022-03-09T09:17:26.000Z"},{"Type":"R","Date":"2022-03-10T11:54:58.000Z"},{"Type":"R","Date":"2022-03-17T14:19:44.000Z"},{"Type":"C","Date":"2022-03-17T14:36:53.000Z"},{"Type":"R","Date":"2022-03-17T15:55:28.000Z"},{"Type":"R","Date":"2022-03-17T16:10:49.000Z"},{"Type":"R","Date":"2022-03-17T16:31:14.000Z"},{"Type":"R","Date":"2022-03-18T10:39:25.000Z"}],"ChurnNumber":5}}