{"number":467,"additions":934,"deletions":189,"changedFiles":32,"createdAt":"2022-11-11T12:46:00Z","merged":true,"mergedAt":"2022-11-11T12:51:24Z","closed":true,"closedAt":"2022-11-11T12:51:24Z","author":{"login":"blair-mongan"},"timelineItems":{"totalCount":6},"commits":{"edges":[{"node":{"commit":{"authoredDate":"2022-11-11T12:43:33Z"}}},{"node":{"commit":{"authoredDate":"2022-11-11T12:44:37Z"}}}]},"reviews":{"edges":[{"node":{"createdAt":"2022-11-11T12:48:29Z","commit":{"authoredDate":"2022-11-11T12:44:37Z"}}}]},"comments":{"edges":[]},"createdAtDate":"2022-11-11T12:46:00.000Z","mergedAtDate":"2022-11-11T12:51:24.000Z","closedAtDate":"2022-11-11T12:51:24.000Z","churn":{"List":[{"Type":"C","Date":"2022-11-11T12:43:33.000Z"},{"Type":"C","Date":"2022-11-11T12:44:37.000Z"},{"Type":"R","Date":"2022-11-11T12:48:29.000Z"}],"ChurnNumber":1}}