{"title":"Adding leaderboard details to stories","repository":{"name":"bracketgame-js"},"number":767,"additions":865,"deletions":58,"changedFiles":13,"createdAt":"2023-08-09T17:39:09Z","merged":true,"mergedAt":"2023-08-10T10:16:36Z","closed":true,"closedAt":"2023-08-10T10:16:36Z","author":{"login":"david-mcb-inc"},"timelineItems":{"totalCount":11},"commits":{"edges":[{"node":{"commit":{"authoredDate":"2023-08-09T17:38:12Z"}}},{"node":{"commit":{"authoredDate":"2023-08-09T20:14:32Z"}}},{"node":{"commit":{"authoredDate":"2023-08-09T20:36:19Z"}}},{"node":{"commit":{"authoredDate":"2023-08-09T20:51:30Z"}}},{"node":{"commit":{"authoredDate":"2023-08-09T20:55:59Z"}}},{"node":{"commit":{"authoredDate":"2023-08-09T20:56:34Z"}}},{"node":{"commit":{"authoredDate":"2023-08-09T21:18:15Z"}}}]},"reviews":{"edges":[{"node":{"createdAt":"2023-08-10T08:08:57Z","commit":{"authoredDate":"2023-08-09T21:18:15Z"}}}]},"comments":{"edges":[]},"createdAtDate":"2023-08-09T17:39:09.000Z","mergedAtDate":"2023-08-10T10:16:36.000Z","closedAtDate":"2023-08-10T10:16:36.000Z","churn":{"List":[{"Type":"C","Date":"2023-08-09T17:38:12.000Z"},{"Type":"C","Date":"2023-08-09T20:14:32.000Z"},{"Type":"C","Date":"2023-08-09T20:36:19.000Z"},{"Type":"C","Date":"2023-08-09T20:51:30.000Z"},{"Type":"C","Date":"2023-08-09T20:55:59.000Z"},{"Type":"C","Date":"2023-08-09T20:56:34.000Z"},{"Type":"C","Date":"2023-08-09T21:18:15.000Z"},{"Type":"R","Date":"2023-08-10T08:08:57.000Z"}],"ChurnNumber":1}}