{"number":149,"additions":61,"deletions":5,"changedFiles":3,"createdAt":"2022-03-02T22:56:55Z","merged":true,"mergedAt":"2022-03-03T09:37:01Z","closed":true,"closedAt":"2022-03-03T09:37:01Z","author":{"login":"blair-mongan"},"timelineItems":{"totalCount":12},"commits":{"edges":[{"node":{"commit":{"authoredDate":"2022-03-02T22:53:59Z"}}}]},"reviews":{"edges":[{"node":{"createdAt":"2022-03-03T08:55:41Z","commit":{"authoredDate":"2022-03-02T22:53:59Z"}}},{"node":{"createdAt":"2022-03-03T08:57:54Z","commit":{"authoredDate":"2022-03-02T22:53:59Z"}}}]},"comments":{"edges":[]},"createdAtDate":"2022-03-02T22:56:55.000Z","mergedAtDate":"2022-03-03T09:37:01.000Z","closedAtDate":"2022-03-03T09:37:01.000Z","churn":{"List":[{"Type":"C","Date":"2022-03-02T22:53:59.000Z"},{"Type":"R","Date":"2022-03-03T08:55:41.000Z"},{"Type":"R","Date":"2022-03-03T08:57:54.000Z"}],"ChurnNumber":1}}