{"title":"Bump @reduxjs/toolkit from 1.9.7 to 2.2.4","repository":{"name":"bracketgame-js"},"number":855,"additions":31,"deletions":16,"changedFiles":2,"createdAt":"2024-05-13T14:02:25Z","merged":false,"mergedAt":null,"closed":true,"closedAt":"2024-05-20T13:49:40Z","author":{"login":"dependabot"},"timelineItems":{"totalCount":6},"commits":{"edges":[{"node":{"commit":{"authoredDate":"2024-05-13T14:02:24Z"}}}]},"reviews":{"edges":[]},"comments":{"edges":[{"node":{"author":{"login":"dependabot"}}}]},"createdAtDate":"2024-05-13T14:02:25.000Z","closedAtDate":"2024-05-20T13:49:40.000Z","churn":{"List":[{"Type":"C","Date":"2024-05-13T14:02:24.000Z"}],"ChurnNumber":0}}