{"title":"Get Token From Parent","repository":{"name":"correctordergame-js"},"number":5,"additions":21,"deletions":10,"changedFiles":4,"createdAt":"2023-08-17T11:10:41Z","merged":true,"mergedAt":"2023-08-17T13:49:36Z","closed":true,"closedAt":"2023-08-17T13:49:36Z","author":{"login":"tompenn-ig"},"timelineItems":{"totalCount":11},"commits":{"edges":[{"node":{"commit":{"authoredDate":"2023-08-17T11:09:20Z"}}},{"node":{"commit":{"authoredDate":"2023-08-17T13:46:25Z"}}}]},"reviews":{"edges":[{"node":{"createdAt":"2023-08-17T11:17:23Z","commit":{"authoredDate":"2023-08-17T11:09:20Z"}}},{"node":{"createdAt":"2023-08-17T13:49:31Z","commit":{"authoredDate":"2023-08-17T13:46:25Z"}}}]},"comments":{"edges":[]},"createdAtDate":"2023-08-17T11:10:41.000Z","mergedAtDate":"2023-08-17T13:49:36.000Z","closedAtDate":"2023-08-17T13:49:36.000Z","churn":{"List":[{"Type":"C","Date":"2023-08-17T11:09:20.000Z"},{"Type":"R","Date":"2023-08-17T11:17:23.000Z"},{"Type":"C","Date":"2023-08-17T13:46:25.000Z"},{"Type":"R","Date":"2023-08-17T13:49:31.000Z"}],"ChurnNumber":2}}