{"number":174,"additions":15,"deletions":9,"changedFiles":3,"createdAt":"2023-01-23T14:37:57Z","merged":true,"mergedAt":"2023-01-23T15:02:36Z","closed":true,"closedAt":"2023-01-23T15:02:36Z","author":{"login":"luke-trimby-ig"},"timelineItems":{"totalCount":9},"commits":{"edges":[{"node":{"commit":{"authoredDate":"2023-01-23T14:02:40Z"}}},{"node":{"commit":{"authoredDate":"2023-01-23T14:32:46Z"}}}]},"reviews":{"edges":[{"node":{"createdAt":"2023-01-23T15:00:06Z","commit":{"authoredDate":"2023-01-23T14:32:46Z"}}}]},"comments":{"edges":[]},"createdAtDate":"2023-01-23T14:37:57.000Z","mergedAtDate":"2023-01-23T15:02:36.000Z","closedAtDate":"2023-01-23T15:02:36.000Z","churn":{"List":[{"Type":"C","Date":"2023-01-23T14:02:40.000Z"},{"Type":"C","Date":"2023-01-23T14:32:46.000Z"},{"Type":"R","Date":"2023-01-23T15:00:06.000Z"}],"ChurnNumber":1}}