{"title":"Call sportsAPI with feedProvider and eventGroupId array/number","repository":{"name":"ig-backend-common"},"number":62,"additions":51,"deletions":1,"changedFiles":2,"createdAt":"2022-11-17T15:13:50Z","merged":true,"mergedAt":"2022-11-18T15:41:48Z","closed":true,"closedAt":"2022-11-18T15:41:48Z","author":{"login":"kb-ig"},"timelineItems":{"totalCount":10},"commits":{"edges":[{"node":{"commit":{"authoredDate":"2022-11-17T15:10:19Z"}}},{"node":{"commit":{"authoredDate":"2022-11-17T15:13:17Z"}}}]},"reviews":{"edges":[{"node":{"createdAt":"2022-11-18T15:33:03Z","commit":{"authoredDate":"2022-11-17T15:13:17Z"}}},{"node":{"createdAt":"2022-11-18T15:39:50Z","commit":{"authoredDate":"2022-11-17T15:13:17Z"}}}]},"comments":{"edges":[]},"createdAtDate":"2022-11-17T15:13:50.000Z","mergedAtDate":"2022-11-18T15:41:48.000Z","closedAtDate":"2022-11-18T15:41:48.000Z","churn":{"List":[{"Type":"C","Date":"2022-11-17T15:10:19.000Z"},{"Type":"C","Date":"2022-11-17T15:13:17.000Z"},{"Type":"R","Date":"2022-11-18T15:33:03.000Z"},{"Type":"R","Date":"2022-11-18T15:39:50.000Z"}],"ChurnNumber":1}}