{"title":"Cd 3458 make history retrieval period configurable","repository":{"name":"jackpotgame-js"},"number":302,"additions":30,"deletions":70,"changedFiles":13,"createdAt":"2022-02-25T14:04:25Z","merged":true,"mergedAt":"2022-02-28T15:04:41Z","closed":true,"closedAt":"2022-02-28T15:04:41Z","author":{"login":"willjatlas"},"timelineItems":{"totalCount":14},"commits":{"edges":[{"node":{"commit":{"authoredDate":"2022-02-25T13:59:41Z"}}},{"node":{"commit":{"authoredDate":"2022-02-25T14:01:31Z"}}},{"node":{"commit":{"authoredDate":"2022-02-28T14:56:03Z"}}}]},"reviews":{"edges":[{"node":{"createdAt":"2022-02-25T16:23:00Z","commit":{"authoredDate":"2022-02-25T14:01:31Z"}}},{"node":{"createdAt":"2022-02-28T13:24:41Z","commit":{"authoredDate":"2022-02-25T14:01:31Z"}}},{"node":{"createdAt":"2022-02-28T14:57:55Z","commit":{"authoredDate":"2022-02-28T14:56:03Z"}}},{"node":{"createdAt":"2022-02-28T15:03:46Z","commit":{"authoredDate":"2022-02-28T14:56:03Z"}}}]},"comments":{"edges":[]},"createdAtDate":"2022-02-25T14:04:25.000Z","mergedAtDate":"2022-02-28T15:04:41.000Z","closedAtDate":"2022-02-28T15:04:41.000Z","churn":{"List":[{"Type":"C","Date":"2022-02-25T13:59:41.000Z"},{"Type":"C","Date":"2022-02-25T14:01:31.000Z"},{"Type":"R","Date":"2022-02-25T16:23:00.000Z"},{"Type":"R","Date":"2022-02-28T13:24:41.000Z"},{"Type":"C","Date":"2022-02-28T14:56:03.000Z"},{"Type":"R","Date":"2022-02-28T14:57:55.000Z"},{"Type":"R","Date":"2022-02-28T15:03:46.000Z"}],"ChurnNumber":2}}