{"title":"Changed header prop for button","repository":{"name":"onetwofreegame-js"},"number":98,"additions":25,"deletions":22,"changedFiles":6,"createdAt":"2022-07-19T08:21:52Z","merged":true,"mergedAt":"2022-07-19T14:44:18Z","closed":true,"closedAt":"2022-07-19T14:44:19Z","author":{"login":"willjatlas"},"timelineItems":{"totalCount":10},"commits":{"edges":[{"node":{"commit":{"authoredDate":"2022-07-19T08:20:04Z"}}},{"node":{"commit":{"authoredDate":"2022-07-19T08:36:05Z"}}},{"node":{"commit":{"authoredDate":"2022-07-19T09:08:20Z"}}}]},"reviews":{"edges":[{"node":{"createdAt":"2022-07-19T11:55:50Z","commit":{"authoredDate":"2022-07-19T09:08:20Z"}}},{"node":{"createdAt":"2022-07-19T14:29:57Z","commit":{"authoredDate":"2022-07-19T09:08:20Z"}}},{"node":{"createdAt":"2022-07-19T14:40:59Z","commit":{"authoredDate":"2022-07-19T09:08:20Z"}}}]},"comments":{"edges":[]},"createdAtDate":"2022-07-19T08:21:52.000Z","mergedAtDate":"2022-07-19T14:44:18.000Z","closedAtDate":"2022-07-19T14:44:19.000Z","churn":{"List":[{"Type":"C","Date":"2022-07-19T08:20:04.000Z"},{"Type":"C","Date":"2022-07-19T08:36:05.000Z"},{"Type":"C","Date":"2022-07-19T09:08:20.000Z"},{"Type":"R","Date":"2022-07-19T11:55:50.000Z"},{"Type":"R","Date":"2022-07-19T14:29:57.000Z"},{"Type":"R","Date":"2022-07-19T14:40:59.000Z"}],"ChurnNumber":1}}