{"title":"feat: adding config for cypress","repository":{"name":"onetwofreegame-js"},"number":424,"additions":39,"deletions":1,"changedFiles":2,"createdAt":"2024-03-12T15:04:41Z","merged":true,"mergedAt":"2024-03-18T13:32:22Z","closed":true,"closedAt":"2024-03-18T13:32:22Z","author":{"login":"alasdairw-incentive"},"timelineItems":{"totalCount":16},"commits":{"edges":[{"node":{"commit":{"authoredDate":"2024-03-12T14:47:57Z"}}},{"node":{"commit":{"authoredDate":"2024-03-12T15:07:52Z"}}},{"node":{"commit":{"authoredDate":"2024-03-12T15:12:46Z"}}},{"node":{"commit":{"authoredDate":"2024-03-12T15:55:50Z"}}},{"node":{"commit":{"authoredDate":"2024-03-12T16:27:17Z"}}},{"node":{"commit":{"authoredDate":"2024-03-12T16:28:40Z"}}},{"node":{"commit":{"authoredDate":"2024-03-12T16:43:53Z"}}}]},"reviews":{"edges":[{"node":{"createdAt":"2024-03-14T16:05:54Z","commit":{"authoredDate":"2024-03-12T16:43:53Z"}}},{"node":{"createdAt":"2024-03-18T11:49:30Z","commit":{"authoredDate":"2024-03-12T16:43:53Z"}}},{"node":{"createdAt":"2024-03-18T12:01:35Z","commit":{"authoredDate":"2024-03-12T16:43:53Z"}}},{"node":{"createdAt":"2024-03-18T12:05:08Z","commit":{"authoredDate":"2024-03-12T16:43:53Z"}}}]},"comments":{"edges":[]},"createdAtDate":"2024-03-12T15:04:41.000Z","mergedAtDate":"2024-03-18T13:32:22.000Z","closedAtDate":"2024-03-18T13:32:22.000Z","churn":{"List":[{"Type":"C","Date":"2024-03-12T14:47:57.000Z"},{"Type":"C","Date":"2024-03-12T15:07:52.000Z"},{"Type":"C","Date":"2024-03-12T15:12:46.000Z"},{"Type":"C","Date":"2024-03-12T15:55:50.000Z"},{"Type":"C","Date":"2024-03-12T16:27:17.000Z"},{"Type":"C","Date":"2024-03-12T16:28:40.000Z"},{"Type":"C","Date":"2024-03-12T16:43:53.000Z"},{"Type":"R","Date":"2024-03-14T16:05:54.000Z"},{"Type":"R","Date":"2024-03-18T11:49:30.000Z"},{"Type":"R","Date":"2024-03-18T12:01:35.000Z"},{"Type":"R","Date":"2024-03-18T12:05:08.000Z"}],"ChurnNumber":1}}