{"title":"CD-8358: Turn off of in play while we release to prod.","repository":{"name":"pick6game-js"},"number":388,"additions":7,"deletions":3,"changedFiles":2,"createdAt":"2023-08-31T07:22:59Z","merged":true,"mergedAt":"2023-08-31T07:35:58Z","closed":true,"closedAt":"2023-08-31T07:35:58Z","author":{"login":"david-mcb-inc"},"timelineItems":{"totalCount":5},"commits":{"edges":[{"node":{"commit":{"authoredDate":"2023-08-31T07:21:31Z"}}}]},"reviews":{"edges":[{"node":{"createdAt":"2023-08-31T07:32:30Z","commit":{"authoredDate":"2023-08-31T07:21:31Z"}}}]},"comments":{"edges":[]},"createdAtDate":"2023-08-31T07:22:59.000Z","mergedAtDate":"2023-08-31T07:35:58.000Z","closedAtDate":"2023-08-31T07:35:58.000Z","churn":{"List":[{"Type":"C","Date":"2023-08-31T07:21:31.000Z"},{"Type":"R","Date":"2023-08-31T07:32:30.000Z"}],"ChurnNumber":1}}