{"title":"CSS changes for fonts and selected state","repository":{"name":"predictorgroupgame-js"},"number":42,"additions":13,"deletions":11,"changedFiles":3,"createdAt":"2024-04-05T13:15:54Z","merged":true,"mergedAt":"2024-04-05T15:27:16Z","closed":true,"closedAt":"2024-04-05T15:27:16Z","author":{"login":"igor570"},"timelineItems":{"totalCount":12},"commits":{"edges":[{"node":{"commit":{"authoredDate":"2024-04-05T13:14:58Z"}}},{"node":{"commit":{"authoredDate":"2024-04-05T14:09:37Z"}}},{"node":{"commit":{"authoredDate":"2024-04-05T14:26:06Z"}}},{"node":{"commit":{"authoredDate":"2024-04-05T14:33:02Z"}}}]},"reviews":{"edges":[{"node":{"createdAt":"2024-04-05T13:51:33Z","commit":{"authoredDate":"2024-04-05T13:14:58Z"}}},{"node":{"createdAt":"2024-04-05T15:10:30Z","commit":{"authoredDate":"2024-04-05T14:33:02Z"}}}]},"comments":{"edges":[]},"createdAtDate":"2024-04-05T13:15:54.000Z","mergedAtDate":"2024-04-05T15:27:16.000Z","closedAtDate":"2024-04-05T15:27:16.000Z","churn":{"List":[{"Type":"C","Date":"2024-04-05T13:14:58.000Z"},{"Type":"R","Date":"2024-04-05T13:51:33.000Z"},{"Type":"C","Date":"2024-04-05T14:09:37.000Z"},{"Type":"C","Date":"2024-04-05T14:26:06.000Z"},{"Type":"C","Date":"2024-04-05T14:33:02.000Z"},{"Type":"R","Date":"2024-04-05T15:10:30.000Z"}],"ChurnNumber":2}}