{"title":"Live showing in header when no predictors active","repository":{"name":"predictorgame-js"},"number":290,"additions":51,"deletions":19,"changedFiles":8,"createdAt":"2020-11-17T13:05:46Z","merged":true,"mergedAt":"2020-11-17T13:59:33Z","closed":true,"closedAt":"2020-11-17T13:59:33Z","author":{"login":"ZombieChowder11"},"timelineItems":{"totalCount":7},"commits":{"edges":[{"node":{"commit":{"authoredDate":"2020-11-17T13:00:04Z"}}},{"node":{"commit":{"authoredDate":"2020-11-17T13:08:03Z"}}}]},"reviews":{"edges":[{"node":{"createdAt":"2020-11-17T13:58:28Z","commit":{"authoredDate":"2020-11-17T13:08:03Z"}}}]},"comments":{"edges":[]},"createdAtDate":"2020-11-17T13:05:46.000Z","mergedAtDate":"2020-11-17T13:59:33.000Z","closedAtDate":"2020-11-17T13:59:33.000Z","churn":{"List":[{"Type":"C","Date":"2020-11-17T13:00:04.000Z"},{"Type":"C","Date":"2020-11-17T13:08:03.000Z"},{"Type":"R","Date":"2020-11-17T13:58:28.000Z"}],"ChurnNumber":1}}