{"title":"Refactor/cd 8220 stats&reveal admin","repository":{"name":"predictorapi"},"number":372,"additions":570,"deletions":356,"changedFiles":6,"createdAt":"2023-08-04T14:37:42Z","merged":true,"mergedAt":"2023-09-08T15:56:57Z","closed":true,"closedAt":"2023-09-08T15:56:57Z","author":{"login":"tompenn-ig"},"timelineItems":{"totalCount":16},"commits":{"edges":[{"node":{"commit":{"authoredDate":"2023-08-04T13:40:54Z"}}},{"node":{"commit":{"authoredDate":"2023-08-04T13:44:29Z"}}},{"node":{"commit":{"authoredDate":"2023-08-04T14:36:36Z"}}},{"node":{"commit":{"authoredDate":"2023-08-08T13:23:30Z"}}},{"node":{"commit":{"authoredDate":"2023-09-08T15:50:59Z"}}}]},"reviews":{"edges":[{"node":{"createdAt":"2023-08-08T12:24:27Z","commit":{"authoredDate":"2023-08-04T14:36:36Z"}}},{"node":{"createdAt":"2023-09-08T15:51:38Z","commit":{"authoredDate":"2023-09-08T15:50:59Z"}}},{"node":{"createdAt":"2023-09-08T15:54:16Z","commit":{"authoredDate":"2023-09-08T15:50:59Z"}}}]},"comments":{"edges":[]},"createdAtDate":"2023-08-04T14:37:42.000Z","mergedAtDate":"2023-09-08T15:56:57.000Z","closedAtDate":"2023-09-08T15:56:57.000Z","churn":{"List":[{"Type":"C","Date":"2023-08-04T13:40:54.000Z"},{"Type":"C","Date":"2023-08-04T13:44:29.000Z"},{"Type":"C","Date":"2023-08-04T14:36:36.000Z"},{"Type":"R","Date":"2023-08-08T12:24:27.000Z"},{"Type":"C","Date":"2023-08-08T13:23:30.000Z"},{"Type":"C","Date":"2023-09-08T15:50:59.000Z"},{"Type":"R","Date":"2023-09-08T15:51:38.000Z"},{"Type":"R","Date":"2023-09-08T15:54:16.000Z"}],"ChurnNumber":2}}