{"title":"adding SportCode to entries and PostPutEntries","repository":{"name":"predictorapi"},"number":303,"additions":21,"deletions":8,"changedFiles":6,"createdAt":"2023-05-17T16:36:27Z","merged":true,"mergedAt":"2023-05-18T09:25:39Z","closed":true,"closedAt":"2023-05-18T09:25:39Z","author":{"login":"Aramosgr"},"timelineItems":{"totalCount":9},"commits":{"edges":[{"node":{"commit":{"authoredDate":"2023-05-17T16:34:08Z"}}},{"node":{"commit":{"authoredDate":"2023-05-18T09:20:21Z"}}}]},"reviews":{"edges":[{"node":{"createdAt":"2023-05-18T09:23:25Z","commit":{"authoredDate":"2023-05-18T09:20:21Z"}}},{"node":{"createdAt":"2023-05-18T09:24:59Z","commit":{"authoredDate":"2023-05-18T09:20:21Z"}}}]},"comments":{"edges":[]},"createdAtDate":"2023-05-17T16:36:27.000Z","mergedAtDate":"2023-05-18T09:25:39.000Z","closedAtDate":"2023-05-18T09:25:39.000Z","churn":{"List":[{"Type":"C","Date":"2023-05-17T16:34:08.000Z"},{"Type":"C","Date":"2023-05-18T09:20:21.000Z"},{"Type":"R","Date":"2023-05-18T09:23:25.000Z"},{"Type":"R","Date":"2023-05-18T09:24:59.000Z"}],"ChurnNumber":1}}