{"number":54,"additions":28,"deletions":28,"createdAt":"2021-09-14T14:25:42Z","merged":false,"mergedAt":null,"closed":true,"closedAt":"2021-09-14T15:08:04Z","author":{"login":"Aramosgr"},"timelineItems":{"totalCount":4},"commits":{"edges":[{"node":{"commit":{"authoredDate":"2021-09-14T14:24:20Z"}}}]},"reviews":{"edges":[{"node":{"createdAt":"2021-09-14T14:26:44Z","commit":{"authoredDate":"2021-09-14T14:24:20Z"}}}]},"comments":{"edges":[]},"createdAtDate":"2021-09-14T14:25:42.000Z","closedAtDate":"2021-09-14T15:08:04.000Z","churn":{"List":[{"Type":"C","Date":"2021-09-14T14:24:20.000Z"},{"Type":"R","Date":"2021-09-14T14:26:44.000Z"}],"ChurnNumber":1}}