{"title":"Added logic fix for validating request active","repository":{"name":"quizapi"},"number":51,"additions":1,"deletions":1,"changedFiles":1,"createdAt":"2021-10-21T13:58:09Z","merged":true,"mergedAt":"2021-10-21T13:59:18Z","closed":true,"closedAt":"2021-10-21T13:59:18Z","author":{"login":"willjatlas"},"timelineItems":{"totalCount":6},"commits":{"edges":[{"node":{"commit":{"authoredDate":"2021-10-21T13:56:02Z"}}}]},"reviews":{"edges":[{"node":{"createdAt":"2021-10-21T13:58:51Z","commit":{"authoredDate":"2021-10-21T13:56:02Z"}}}]},"comments":{"edges":[]},"createdAtDate":"2021-10-21T13:58:09.000Z","mergedAtDate":"2021-10-21T13:59:18.000Z","closedAtDate":"2021-10-21T13:59:18.000Z","churn":{"List":[{"Type":"C","Date":"2021-10-21T13:56:02.000Z"},{"Type":"R","Date":"2021-10-21T13:58:51.000Z"}],"ChurnNumber":1}}