{"title":"Translation for result and removing countdown var","repository":{"name":"racinggame-js"},"number":51,"additions":81,"deletions":55,"changedFiles":29,"createdAt":"2023-05-11T12:51:07Z","merged":true,"mergedAt":"2023-05-11T16:14:35Z","closed":true,"closedAt":"2023-05-11T16:14:35Z","author":{"login":"tompenn-ig"},"timelineItems":{"totalCount":9},"commits":{"edges":[{"node":{"commit":{"authoredDate":"2023-05-11T12:50:26Z"}}}]},"reviews":{"edges":[{"node":{"createdAt":"2023-05-11T12:59:36Z","commit":{"authoredDate":"2023-05-11T12:50:26Z"}}},{"node":{"createdAt":"2023-05-11T16:14:15Z","commit":{"authoredDate":"2023-05-11T12:50:26Z"}}}]},"comments":{"edges":[]},"createdAtDate":"2023-05-11T12:51:07.000Z","mergedAtDate":"2023-05-11T16:14:35.000Z","closedAtDate":"2023-05-11T16:14:35.000Z","churn":{"List":[{"Type":"C","Date":"2023-05-11T12:50:26.000Z"},{"Type":"R","Date":"2023-05-11T12:59:36.000Z"},{"Type":"R","Date":"2023-05-11T16:14:15.000Z"}],"ChurnNumber":1}}