{"title":"feature/CD-10799_UpdatePrizeScreenToUseWorldOfWonkaSlotv2","repository":{"name":"reelmoneygame-js"},"number":424,"additions":366,"deletions":129,"changedFiles":17,"createdAt":"2024-06-03T14:05:17Z","merged":true,"mergedAt":"2024-06-04T14:38:51Z","closed":true,"closedAt":"2024-06-04T14:38:51Z","author":{"login":"RyanIncentiveGames"},"timelineItems":{"totalCount":18},"commits":{"edges":[{"node":{"commit":{"authoredDate":"2024-05-30T12:23:44Z"}}},{"node":{"commit":{"authoredDate":"2024-05-30T14:28:18Z"}}},{"node":{"commit":{"authoredDate":"2024-05-30T15:36:39Z"}}},{"node":{"commit":{"authoredDate":"2024-06-03T10:29:43Z"}}},{"node":{"commit":{"authoredDate":"2024-06-03T10:36:58Z"}}},{"node":{"commit":{"authoredDate":"2024-06-03T13:53:58Z"}}},{"node":{"commit":{"authoredDate":"2024-06-03T14:00:24Z"}}},{"node":{"commit":{"authoredDate":"2024-06-04T13:53:32Z"}}},{"node":{"commit":{"authoredDate":"2024-06-04T13:56:52Z"}}},{"node":{"commit":{"authoredDate":"2024-06-04T14:34:16Z"}}}]},"reviews":{"edges":[{"node":{"createdAt":"2024-06-04T14:38:45Z","commit":{"authoredDate":"2024-06-04T14:34:16Z"}}}]},"comments":{"edges":[]},"createdAtDate":"2024-06-03T14:05:17.000Z","mergedAtDate":"2024-06-04T14:38:51.000Z","closedAtDate":"2024-06-04T14:38:51.000Z","churn":{"List":[{"Type":"C","Date":"2024-05-30T12:23:44.000Z"},{"Type":"C","Date":"2024-05-30T14:28:18.000Z"},{"Type":"C","Date":"2024-05-30T15:36:39.000Z"},{"Type":"C","Date":"2024-06-03T10:29:43.000Z"},{"Type":"C","Date":"2024-06-03T10:36:58.000Z"},{"Type":"C","Date":"2024-06-03T13:53:58.000Z"},{"Type":"C","Date":"2024-06-03T14:00:24.000Z"},{"Type":"C","Date":"2024-06-04T13:53:32.000Z"},{"Type":"C","Date":"2024-06-04T13:56:52.000Z"},{"Type":"C","Date":"2024-06-04T14:34:16.000Z"},{"Type":"R","Date":"2024-06-04T14:38:45.000Z"}],"ChurnNumber":1}}