{"title":"CD-11610 - Added jackpotdev segment","repository":{"name":"slotapi"},"number":601,"additions":156,"deletions":0,"changedFiles":1,"createdAt":"2024-08-27T13:39:48Z","merged":true,"mergedAt":"2024-08-28T09:07:59Z","closed":true,"closedAt":"2024-08-28T09:08:00Z","author":{"login":"kb-ig"},"timelineItems":{"totalCount":10},"commits":{"edges":[{"node":{"commit":{"authoredDate":"2024-08-27T13:34:49Z"}}},{"node":{"commit":{"authoredDate":"2024-08-27T13:36:29Z"}}}]},"reviews":{"edges":[{"node":{"createdAt":"2024-08-27T15:34:44Z","commit":{"authoredDate":"2024-08-27T13:36:29Z"}}}]},"comments":{"edges":[]},"createdAtDate":"2024-08-27T13:39:48.000Z","mergedAtDate":"2024-08-28T09:07:59.000Z","closedAtDate":"2024-08-28T09:08:00.000Z","churn":{"List":[{"Type":"C","Date":"2024-08-27T13:34:49.000Z"},{"Type":"C","Date":"2024-08-27T13:36:29.000Z"},{"Type":"R","Date":"2024-08-27T15:34:44.000Z"}],"ChurnNumber":1}}