{"title":"Added support for multiple external events mapping to the same intern…","repository":{"name":"sportsapi"},"number":23,"additions":5,"deletions":5,"changedFiles":1,"createdAt":"2021-01-12T13:58:33Z","merged":true,"mergedAt":"2021-01-12T14:03:45Z","closed":true,"closedAt":"2021-01-12T14:03:45Z","author":{"login":"blair-mongan"},"timelineItems":{"totalCount":5},"commits":{"edges":[{"node":{"commit":{"authoredDate":"2021-01-12T13:58:10Z"}}}]},"reviews":{"edges":[{"node":{"createdAt":"2021-01-12T14:00:46Z","commit":{"authoredDate":"2021-01-12T13:58:10Z"}}}]},"comments":{"edges":[]},"createdAtDate":"2021-01-12T13:58:33.000Z","mergedAtDate":"2021-01-12T14:03:45.000Z","closedAtDate":"2021-01-12T14:03:45.000Z","churn":{"List":[{"Type":"C","Date":"2021-01-12T13:58:10.000Z"},{"Type":"R","Date":"2021-01-12T14:00:46.000Z"}],"ChurnNumber":1}}