{"title":"add symbolic link for FB sportscode to redirect","repository":{"name":"teamsgame-js"},"number":198,"additions":1,"deletions":0,"changedFiles":1,"createdAt":"2024-07-30T09:40:39Z","merged":false,"mergedAt":null,"closed":true,"closedAt":"2024-07-30T14:38:54Z","author":{"login":"brandon-incentivegames"},"timelineItems":{"totalCount":6},"commits":{"edges":[{"node":{"commit":{"authoredDate":"2024-07-30T09:38:45Z"}}}]},"reviews":{"edges":[]},"comments":{"edges":[{"node":{"author":{"login":"cypress"}}}]},"createdAtDate":"2024-07-30T09:40:39.000Z","closedAtDate":"2024-07-30T14:38:54.000Z","churn":{"List":[{"Type":"C","Date":"2024-07-30T09:38:45.000Z"}],"ChurnNumber":0}}