{"title":"CD 11743 - Velocity Free: Prize Win Test Screen","repository":{"name":"velocityfreegame-js"},"number":61,"additions":169,"deletions":56,"changedFiles":23,"createdAt":"2024-09-05T08:54:42Z","merged":true,"mergedAt":"2024-09-05T09:27:39Z","closed":true,"closedAt":"2024-09-05T09:27:39Z","author":{"login":"christophercaleb"},"timelineItems":{"totalCount":19},"commits":{"edges":[{"node":{"commit":{"authoredDate":"2024-09-04T18:03:16Z"}}},{"node":{"commit":{"authoredDate":"2024-09-04T19:41:04Z"}}},{"node":{"commit":{"authoredDate":"2024-09-04T19:42:50Z"}}},{"node":{"commit":{"authoredDate":"2024-09-04T20:17:26Z"}}},{"node":{"commit":{"authoredDate":"2024-09-05T09:20:18Z"}}},{"node":{"commit":{"authoredDate":"2024-09-05T09:23:36Z"}}}]},"reviews":{"edges":[{"node":{"createdAt":"2024-09-05T09:21:17Z","commit":{"authoredDate":"2024-09-05T09:20:18Z"}}},{"node":{"createdAt":"2024-09-05T09:24:19Z","commit":{"authoredDate":"2024-09-05T09:23:36Z"}}}]},"comments":{"edges":[]},"createdAtDate":"2024-09-05T08:54:42.000Z","mergedAtDate":"2024-09-05T09:27:39.000Z","closedAtDate":"2024-09-05T09:27:39.000Z","churn":{"List":[{"Type":"C","Date":"2024-09-04T18:03:16.000Z"},{"Type":"C","Date":"2024-09-04T19:41:04.000Z"},{"Type":"C","Date":"2024-09-04T19:42:50.000Z"},{"Type":"C","Date":"2024-09-04T20:17:26.000Z"},{"Type":"C","Date":"2024-09-05T09:20:18.000Z"},{"Type":"R","Date":"2024-09-05T09:21:17.000Z"},{"Type":"C","Date":"2024-09-05T09:23:36.000Z"},{"Type":"R","Date":"2024-09-05T09:24:19.000Z"}],"ChurnNumber":2}}