{"title":"CD-12503_bet365Logo: Changed the logo for bet365 and fixed the header…","repository":{"name":"velocitygame-js"},"number":524,"additions":6,"deletions":4,"changedFiles":5,"createdAt":"2024-11-28T12:09:00Z","merged":true,"mergedAt":"2024-11-28T13:55:11Z","closed":true,"closedAt":"2024-11-28T13:55:11Z","author":{"login":"DavidGGibson"},"timelineItems":{"totalCount":17},"commits":{"edges":[{"node":{"commit":{"authoredDate":"2024-11-28T12:07:37Z"}}},{"node":{"commit":{"authoredDate":"2024-11-28T13:20:43Z"}}},{"node":{"commit":{"authoredDate":"2024-11-28T13:40:06Z"}}}]},"reviews":{"edges":[{"node":{"createdAt":"2024-11-28T12:10:02Z","commit":{"authoredDate":"2024-11-28T12:07:37Z"}}},{"node":{"createdAt":"2024-11-28T12:18:53Z","commit":{"authoredDate":"2024-11-28T12:07:37Z"}}},{"node":{"createdAt":"2024-11-28T12:19:12Z","commit":{"authoredDate":"2024-11-28T12:07:37Z"}}},{"node":{"createdAt":"2024-11-28T13:03:38Z","commit":{"authoredDate":"2024-11-28T12:07:37Z"}}},{"node":{"createdAt":"2024-11-28T13:04:41Z","commit":{"authoredDate":"2024-11-28T12:07:37Z"}}},{"node":{"createdAt":"2024-11-28T13:44:03Z","commit":{"authoredDate":"2024-11-28T13:40:06Z"}}},{"node":{"createdAt":"2024-11-28T13:53:50Z","commit":{"authoredDate":"2024-11-28T13:40:06Z"}}}]},"comments":{"edges":[]},"createdAtDate":"2024-11-28T12:09:00.000Z","mergedAtDate":"2024-11-28T13:55:11.000Z","closedAtDate":"2024-11-28T13:55:11.000Z","churn":{"List":[{"Type":"C","Date":"2024-11-28T12:07:37.000Z"},{"Type":"R","Date":"2024-11-28T12:10:02.000Z"},{"Type":"R","Date":"2024-11-28T12:18:53.000Z"},{"Type":"R","Date":"2024-11-28T12:19:12.000Z"},{"Type":"R","Date":"2024-11-28T13:03:38.000Z"},{"Type":"R","Date":"2024-11-28T13:04:41.000Z"},{"Type":"C","Date":"2024-11-28T13:20:43.000Z"},{"Type":"C","Date":"2024-11-28T13:40:06.000Z"},{"Type":"R","Date":"2024-11-28T13:44:03.000Z"},{"Type":"R","Date":"2024-11-28T13:53:50.000Z"}],"ChurnNumber":2}}