{"title":"fix/CD-00000-handle-early-ft: Refactor socket logic to handle out of …","repository":{"name":"velocitygame-js"},"number":346,"additions":27,"deletions":9,"changedFiles":1,"createdAt":"2024-09-09T15:07:04Z","merged":true,"mergedAt":"2024-09-09T15:54:29Z","closed":true,"closedAt":"2024-09-09T15:54:29Z","author":{"login":"corrie-mcgregor"},"timelineItems":{"totalCount":9},"commits":{"edges":[{"node":{"commit":{"authoredDate":"2024-09-09T15:06:13Z"}}}]},"reviews":{"edges":[{"node":{"createdAt":"2024-09-09T15:35:42Z","commit":{"authoredDate":"2024-09-09T15:06:13Z"}}},{"node":{"createdAt":"2024-09-09T15:37:00Z","commit":{"authoredDate":"2024-09-09T15:06:13Z"}}},{"node":{"createdAt":"2024-09-09T15:46:05Z","commit":{"authoredDate":"2024-09-09T15:06:13Z"}}}]},"comments":{"edges":[]},"createdAtDate":"2024-09-09T15:07:04.000Z","mergedAtDate":"2024-09-09T15:54:29.000Z","closedAtDate":"2024-09-09T15:54:29.000Z","churn":{"List":[{"Type":"C","Date":"2024-09-09T15:06:13.000Z"},{"Type":"R","Date":"2024-09-09T15:35:42.000Z"},{"Type":"R","Date":"2024-09-09T15:37:00.000Z"},{"Type":"R","Date":"2024-09-09T15:46:05.000Z"}],"ChurnNumber":1}}