{"number":137,"additions":12,"deletions":7,"changedFiles":6,"createdAt":"2020-05-21T11:10:15Z","merged":true,"mergedAt":"2020-05-21T11:11:38Z","closed":true,"closedAt":"2020-05-21T11:11:38Z","author":{"login":"Aramosgr"},"timelineItems":{"totalCount":4},"commits":{"edges":[{"node":{"commit":{"authoredDate":"2020-05-21T11:08:11Z"}}}]},"reviews":{"edges":[]},"comments":{"edges":[]},"createdAtDate":"2020-05-21T11:10:15.000Z","mergedAtDate":"2020-05-21T11:11:38.000Z","closedAtDate":"2020-05-21T11:11:38.000Z","churn":{"List":[{"Type":"C","Date":"2020-05-21T11:08:11.000Z"}],"ChurnNumber":0}}