{"title":"fixing autostake width for Betway","repository":{"name":"vsportsgame-js"},"number":193,"additions":11,"deletions":10,"changedFiles":2,"createdAt":"2020-08-04T14:32:19Z","merged":true,"mergedAt":"2020-08-04T14:33:00Z","closed":true,"closedAt":"2020-08-04T14:33:00Z","author":{"login":"Aramosgr"},"timelineItems":{"totalCount":6},"commits":{"edges":[{"node":{"commit":{"authoredDate":"2020-08-04T14:31:03Z"}}},{"node":{"commit":{"authoredDate":"2020-08-04T14:32:08Z"}}}]},"reviews":{"edges":[{"node":{"createdAt":"2020-08-04T14:32:55Z","commit":{"authoredDate":"2020-08-04T14:32:08Z"}}}]},"comments":{"edges":[]},"createdAtDate":"2020-08-04T14:32:19.000Z","mergedAtDate":"2020-08-04T14:33:00.000Z","closedAtDate":"2020-08-04T14:33:00.000Z","churn":{"List":[{"Type":"C","Date":"2020-08-04T14:31:03.000Z"},{"Type":"C","Date":"2020-08-04T14:32:08.000Z"},{"Type":"R","Date":"2020-08-04T14:32:55.000Z"}],"ChurnNumber":1}}